{
  "background": "school.png",
  "actions": [
    {
      "type": "play_sound"
    },
    {
      "type": "sub",
      "target": "Lucy",
      "position": 0
    },
    {
      "type": "sub",
      "target": "Gryphon",
      "position": 1
    },
    {
      "type": "speech",
      "target": "Lucy",
      "text": "Hello, how are you doing?"
    },
    {
      "type": "speech",
      "target": "Gryphon",
      "text": "Incredible, anyway as I was saying..."
    },
    {
      "type": "texture",
      "target": "Lucy",
      "texture": "angry"
    },
    {
      "type": "speech",
      "target": "Lucy",
      "text": "That's great! I also believe that we must raise taxes on single mothers. Particularly the struggling kind, haha!"
    },
    {
      "type": "texture",
      "target": "Lucy",
      "texture": "neutral"
    },
    {
      "type": "speech",
      "target": "Lucy",
      "text": "It's fantastic to speak with people who have similar views :D"
    },
    {
      "type": "texture",
      "target": "Gryphon",
      "texture": "angry"
    },
    {
      "type": "speech",
      "target": "Gryphon",
      "text": "Hey Lucy you interrupted me you insolent fool I will smite you down with the ultimate impostor technique so fear for your life!"
    },
    {
      "type": "texture",
      "target": "Gryphon",
      "texture": "neutral"
    },
    {
      "type": "sub",
      "target": "Gryphon",
      "position": 0
    },
    {
      "type": "speech",
      "target": "Gryphon",
      "text": "obama"
    },
    {
      "type": "sub",
      "target": null,
      "position": 0
    }
  ]
}
